py.typed
codat_assess/__init__.py
codat_assess/_hooks/__init__.py
codat_assess/_hooks/registration.py
codat_assess/_hooks/sdkhooks.py
codat_assess/_hooks/types.py
codat_assess/basesdk.py
codat_assess/data_integrity.py
codat_assess/excel_reports.py
codat_assess/httpclient.py
codat_assess/models/errors/__init__.py
codat_assess/models/errors/errormessage.py
codat_assess/models/errors/sdkerror.py
codat_assess/models/operations/__init__.py
codat_assess/models/operations/generate_excel_report.py
codat_assess/models/operations/generate_loan_summary.py
codat_assess/models/operations/generate_loan_transactions.py
codat_assess/models/operations/get_accounting_marketing_metrics.py
codat_assess/models/operations/get_accounts_for_enhanced_balance_sheet.py
codat_assess/models/operations/get_accounts_for_enhanced_profit_and_loss.py
codat_assess/models/operations/get_commerce_customer_retention_metrics.py
codat_assess/models/operations/get_commerce_lifetime_value_metrics.py
codat_assess/models/operations/get_commerce_orders_metrics.py
codat_assess/models/operations/get_commerce_refunds_metrics.py
codat_assess/models/operations/get_commerce_revenue_metrics.py
codat_assess/models/operations/get_data_integrity_status.py
codat_assess/models/operations/get_data_integrity_summaries.py
codat_assess/models/operations/get_enhanced_cash_flow_transactions.py
codat_assess/models/operations/get_enhanced_invoices_report.py
codat_assess/models/operations/get_excel_report.py
codat_assess/models/operations/get_excel_report_generation_status.py
codat_assess/models/operations/get_loan_summary.py
codat_assess/models/operations/get_recurring_revenue_metrics.py
codat_assess/models/operations/list_data_type_data_integrity_details.py
codat_assess/models/operations/list_loan_transactions.py
codat_assess/models/operations/request_recurring_revenue_metrics.py
codat_assess/models/shared/__init__.py
codat_assess/models/shared/accountcategoriesupdatedwebhook.py
codat_assess-0.34.0.dist-info/METADATA
codat_assess-0.34.0.dist-info/WHEEL
codat_assess-0.34.0.dist-info/RECORD
